{
    "passenv": {
        "branch": "master",
        "description": "Fetches secrets from your password store and adds them to your environment.",
        "homepage": "https://splintah.github.io/passenv/",
        "owner": "splintah",
        "repo": "passenv",
        "rev": "00f6d61f741a6928984477b7da07c421be77ec85",
        "sha256": "0qizkg5rhiiyj9hxd6iby18nypwxas0ypfzd5hm7b6djj8nnv7zc",
        "type": "tarball",
        "url": "https://github.com/splintah/passenv/archive/00f6d61f741a6928984477b7da07c421be77ec85.tar.gz",
        "url_template": "https://github.com/<owner>/<repo>/archive/<rev>.tar.gz"
    }
}
